Workbook

Sheet INÍCIO
A1: ORGANIZADOR PARA DECLARAÇÃO DE IMPOSTO DE RENDA
A3: Centralize e organize as informações necessárias para sua declaração.
A5: MENU PRINCIPAL
A7: =HYPERLINK("#'DADOS_PESSOAIS'!A1","DADOS PESSOAIS") -> DADOS PESSOAIS | E7: =HYPERLINK("#'INFORMES'!A1","INFORMES") -> INFORMES | I7: =HYPERLINK("#'RENDIMENTOS'!A1","RENDIMENTOS") -> RENDIMENTOS
A11: =HYPERLINK("#'BENS_DIREITOS'!A1","BENS E DIREITOS") -> BENS E DIREITOS | E11: =HYPERLINK("#'PAGAMENTOS'!A1","PAGAMENTOS") -> PAGAMENTOS | I11: =HYPERLINK("#'RESUMO'!A1","RESUMO") -> RESUMO
A16: STATUS DO PREENCHIMENTO
A18: Indicador | B18: Status / Quantidade | F18: Pagamentos cadastrados
A19: Dados pessoais preenchidos | B19: =IF(COUNTA(DADOS_PESSOAIS!B8:B24)>=8,"OK","PENDENTE") -> PENDENTE | F19: =COUNTIF(PAGAMENTOS!A10:A109,"<>") -> 1
A20: Informes cadastrados | B20: =COUNTIF(INFORMES!A10:A109,"<>") -> 1
A21: Rendimentos cadastrados | B21: =COUNTIF(RENDIMENTOS!A10:A159,"<>") -> 1
A22: Bens cadastrados | B22: =COUNTIF(BENS_DIREITOS!A10:A109,"<>") -> 1

Sheet DADOS_PESSOAIS
A1: DADOS PESSOAIS
A3: Cadastre os dados básicos do titular.
A5: =HYPERLINK("#'INÍCIO'!A1","← VOLTAR AO MENU") -> ← VOLTAR AO MENU
A7: Nome completo
A8: CPF
A9: Data de nascimento
A10: Título de eleitor
A11: Telefone
A12: E mail
A13: CEP
A14: Endereço
A15: Número
A16: Complemento
A17: Bairro
A18: Cidade
... A24: CPF do cônjuge

Sheet INFORMES
A1: INFORMES DE RENDIMENTOS
A3: Controle os documentos recebidos de instituições e fontes pagadoras.
A5: =HYPERLINK("#'INÍCIO'!A1","← VOLTAR AO MENU") -> ← VOLTAR AO MENU
A7: Indicador | B7: Valor | D7: Indicador | E7: Valor
A8: Quantidade de informes | B8: =COUNTIF(A10:A109,"<>") -> 1 | D8: Valor total informado | E8: =SUM(E10:E109) -> 0
A10: Instituição | B10: CNPJ | C10: Tipo de informe | D10: Ano calendário | E10: Valor informado | F10: Arquivo recebido? | G10: Observações

Sheet RENDIMENTOS
A1: RENDIMENTOS
A3: Organize rendimentos e retenções por fonte pagadora.
A5: =HYPERLINK("#'INÍCIO'!A1","← VOLTAR AO MENU") -> ← VOLTAR AO MENU
A7: Indicador | B7: Valor | D7: Indicador | E7: Valor
A8: Total de rendimentos | B8: =SUM(E11:E159) -> 0 | D8: Total de imposto retido | E8: =SUM(F11:F159) -> 0
A10: Fonte pagadora | B10: CPF ou CNPJ | C10: Categoria | D10: Descrição | E10: Valor | F10: Imposto retido | G10: Observações

Sheet BENS_DIREITOS
A1: BENS E DIREITOS
A3: Acompanhe a posição patrimonial entre os anos.
A5: =HYPERLINK("#'INÍCIO'!A1","← VOLTAR AO MENU") -> ← VOLTAR AO MENU
A7: Patrimônio ano anterior | B7: Patrimônio ano atual | C7: Variação patrimonial
A8: =SUM(D11:D109) -> 0 | B8: =SUM(E11:E109) -> 0 | C8: =B8-A8 -> 0
A10: Categoria | B10: Descrição do bem | C10: CPF ou CNPJ relacionado | D10: Situação em 31/12 ano anterior | E10: Situação em 31/12 ano atual | F10: Banco ou instituição | G10: Observações

Sheet PAGAMENTOS
A1: PAGAMENTOS
A3: Registre despesas e pagamentos relevantes para conferência.
A5: =HYPERLINK("#'INÍCIO'!A1","← VOLTAR AO MENU") -> ← VOLTAR AO MENU
A7: Indicador | B7: Valor
A8: Total de pagamentos | B8: =SUM(E11:E109) -> 0
A10: Tipo | B10: Beneficiário | C10: CPF ou CNPJ | D10: Descrição | E10: Valor pago | F10: Possui comprovante? | G10: Observações

Sheet RESUMO
A1: RESUMO DA DECLARAÇÃO
A3: Visão consolidada dos dados cadastrados.
A5: =HYPERLINK("#'INÍCIO'!A1","← VOLTAR AO MENU") -> ← VOLTAR AO MENU
A7: ="Total de informes"&CHAR(10)&COUNTIF(INFORMES!A11:A109,"<>") -> Total de informes 0 | E7: ="Total de rendimentos"&CHAR(10)&TEXT(SUM(RENDIMENTOS!E11:E159),"R$ #,##0.00") -> Total de rendimentos R$ ,000 | I7: ="Imposto retido"&CHAR(10)&TEXT(SUM(RENDIMENTOS!F11:F159),"R$ #,##0.00") -> Imposto retido R$ ,000
A11: ="Patrimônio atual"&CHAR(10)&TEXT(SUM(BENS_DIREITOS!E11:E109),"R$ #,##0.00") -> Patrimônio atual R$ ,000 | E11: ="Variação patrimonial"&CHAR(10)&TEXT(SUM(BENS_DIREITOS!E11:E109)-SUM(BENS_DIREITOS!D11:D109),"R$ #,##0.00") -> Variação patrimonial R$ ,000 | I11: ="Total de pagamentos"&CHAR(10)&TEXT(SUM(PAGAMENTOS!E11:E109),"R$ #,##0.00") -> Total de pagamentos R$ ,000
A16: CHECKLIST DA DECLARAÇÃO
A18: Área | B18: Status | D18: Área | E18: Status
A19: Dados pessoais | B19: =IF(COUNTA(DADOS_PESSOAIS!B7:B24)>=8,"OK","PENDENTE") -> PENDENTE | D19: Pagamentos | E19: =IF(COUNTIF(PAGAMENTOS!A11:A109,"<>")>0,"OK","PENDENTE") -> PENDENTE
A20: Informes | B20: =IF(COUNTIF(INFORMES!A11:A109,"<>")>0,"OK","PENDENTE") -> PENDENTE
A21: Rendimentos | B21: =IF(COUNTIF(RENDIMENTOS!A11:A159,"<>")>0,"OK","PENDENTE") -> PENDENTE
A22: Bens e Direitos | B22: =IF(COUNTIF(BENS_DIREITOS!A11:A109,"<>")>0,"OK","PENDENTE") -> PENDENTE
A26: Categoria | B26: Total | D26: Categoria | E26: Patrimônio
A27: Salário | B27: =SUMIF(RENDIMENTOS!$C$11:$C$159,A27,RENDIMENTOS!$E$11:$E$159) -> 0 | D27: Imóvel | E27: =SUMIF(BENS_DIREITOS!$A$11:$A$109,D27,BENS_DIREITOS!$E$11:$E$109) -> 0
A28: Pró labore | B28: =SUMIF(RENDIMENTOS!$C$11:$C$159,A28,RENDIMENTOS!$E$11:$E$159) -> 0 | D28: Veículo | E28: =SUMIF(BENS_DIREITOS!$A$11:$A$109,D28,BENS_DIREITOS!$E$11:$E$109) -> 0
A29: Aposentadoria | B29: =SUMIF(RENDIMENTOS!$C$11:$C$159,A29,RENDIMENTOS!$E$11:$E$159) -> 0 | D29: Conta bancária | E29: =SUMIF(BENS_DIREITOS!$A$11:$A$109,D29,BENS_DIREITOS!$E$11:$E$109) -> 0
A30: Aluguel | B30: =SUMIF(RENDIMENTOS!$C$11:$C$159,A30,RENDIMENTOS!$E$11:$E$159) -> 0 | D30: Investimento | E30: =SUMIF(BENS_DIREITOS!$A$11:$A$109,D30,BENS_DIREITOS!$E$11:$E$109) -> 0
A31: Rendimento financeiro | B31: =SUMIF(RENDIMENTOS!$C$11:$C$159,A31,RENDIMENTOS!$E$11:$E$159) -> 0 | D31: Participação societária | E31: =SUMIF(BENS_DIREITOS!$A$11:$A$109,D31,BENS_DIREITOS!$E$11:$E$109) -> 0
A32: Dividendos | B32: =SUMIF(RENDIMENTOS!$C$11:$C$159,A32,RENDIMENTOS!$E$11:$E$159) -> 0 | D32: Criptoativo | E32: =SUMIF(BENS_DIREITOS!$A$11:$A$109,D32,BENS_DIREITOS!$E$11:$E$109) -> 0
A33: Juros sobre capital | B33: =SUMIF(RENDIMENTOS!$C$11:$C$159,A33,RENDIMENTOS!$E$11:$E$159) -> 0 | D33: Outros | E33: =SUMIF(BENS_DIREITOS!$A$11:$A$109,D33,BENS_DIREITOS!$E$11:$E$109) -> 0
A34: Rendimento isento | B34: =SUMIF(RENDIMENTOS!$C$11:$C$159,A34,RENDIMENTOS!$E$11:$E$159) -> 0
A35: Outros | B35: =SUMIF(RENDIMENTOS!$C$11:$C$159,A35,RENDIMENTOS!$E$11:$E$159) -> 0

Sheet LISTAS
A1: UF | B1: Estado Civil | C1: SimNão | D1: Tipo Informe | E1: Categoria Rendimento | F1: Categoria Bem | G1: Tipo Pagamento
A2: AC | B2: Solteiro(a) | C2: Sim | D2: Banco | E2: Salário | F2: Imóvel | G2: Saúde
A3: AL | B3: Casado(a) | C3: Não | D3: Corretora | E3: Pró labore | F3: Veículo | G3: Educação
A4: AP | B4: Divorciado(a) | D4: Empregador | E4: Aposentadoria | F4: Conta bancária | G4: Previdência
A5: AM | B5: Viúvo(a) | D5: Previdência | E5: Aluguel | F5: Investimento | G5: Pensão alimentícia
A6: BA | B6: União estável | D6: Plano de saúde | E6: Rendimento financeiro | F6: Participação societária | G6: Doação
A7: CE | B7: Separado(a) | D7: Outros | E7: Dividendos | F7: Criptoativo | G7: Honorários
A8: DF | E8: Juros sobre capital | F8: Outros | G8: Outros
A9: ES | E9: Rendimento isento
A10: GO | E10: Outros
A11: MA
A12: MT
A13: MS
A14: MG
A15: PA
A16: PB
A17: PR
A18: PE
A19: PI
A20: RJ
A21: RN
A22: RS
... A28: TO
